.gitignore
.travis.yml
LICENSE
Pipfile
Pipfile.lock
README.md
setup.py
edinet/__init__.py
edinet/facade.py
edinet/xbrl_feature.py
edinet/xbrl_file.py
edinet/client/base_client.py
edinet/client/document_client.py
edinet/client/document_list_client.py
edinet/models/__init__.py
edinet/models/document.py
edinet/models/documents.py
edinet/models/error_response.py
edinet/models/metadata.py
edinet/parser/__init__.py
edinet/parser/xbrl_parser.py
edinet/parser/aspects/__init__.py
edinet/parser/aspects/business.py
edinet/parser/aspects/company.py
edinet/parser/aspects/finance.py
edinet/parser/aspects/information.py
edinet/parser/aspects/metadata.py
edinet_python.egg-info/PKG-INFO
edinet_python.egg-info/SOURCES.txt
edinet_python.egg-info/dependency_links.txt
edinet_python.egg-info/requires.txt
edinet_python.egg-info/top_level.txt
tests/__init__.py
tests/test_api.py
tests/test_parse.py
tests/test_xbrl_file.py
tests/utils.py
tests/client/__init__.py
tests/client/test_document.py
tests/client/test_document_list_client.py
tests/data/test_example_1.pdf
tests/data/xbrl2018.xbrl
tests/data/xbrl2019.xbrl
tests/model/__init__.py
tests/model/test_document.py
tests/parser/__init__.py
tests/parser/test_xbrl_parser.py
tests/parser/aspects/__init__.py
tests/parser/aspects/test_business.py
tests/parser/aspects/test_company.py
tests/parser/aspects/test_finance.py
tests/parser/aspects/test_information.py
tests/parser/aspects/test_metadata.py