Metadata-Version: 2.1
Name: edinet-python
Version: 0.1.17
Summary: EDINET API Client for Python.
Home-page: https://github.com/chakki-works/edinet-python
Author: icoxfog417
Author-email: icoxfog417@yahoo.co.jp
License: MIT
Keywords: EDINET,API
Platform: UNKNOWN
Provides-Extra: statements
